SQUANCH-1.1.0.dist-info/METADATA
SQUANCH-1.1.0.dist-info/RECORD
SQUANCH-1.1.0.dist-info/WHEEL
SQUANCH-1.1.0.dist-info/top_level.txt
squanch/__init__.py
squanch/agent.py
squanch/channels.py
squanch/errors.py
squanch/gates.py
squanch/linalg.py
squanch/qstream.py
squanch/qubit.py
squanch/simulate.py
