Metadata-Version: 2.1
Name: SQUANCH
Version: 1.1.0
Summary: Simulator for Quantum Networks and Channels
Home-page: https://github.com/att-innovate/squanch
Author: Ben Bartlett
Author-email: benbartlett@stanford.edu
License: MIT
Platform: UNKNOWN
Classifier: Programming Language :: Python :: 3
Classifier: License :: OSI Approved :: MIT License
Classifier: Operating System :: OS Independent
